MyLyric/Lyric_Time_tab.py
MyLyric/Lyric_character.py
MyLyric/Lyric_file.py
MyLyric/Lyric_line.py
MyLyric/Lyric_line_content.py
MyLyric/__init__.py
MyLyric-3.0.0.dist-info/LICENSE
MyLyric-3.0.0.dist-info/METADATA
MyLyric-3.0.0.dist-info/WHEEL
MyLyric-3.0.0.dist-info/top_level.txt
MyLyric-3.0.0.dist-info/RECORD
